docai/__init__.py
docai/annotations/__init__.py
docai/annotations/annotation_client.py
docai/annotations/annotations.py
docai/annotations/bbx_utils.py
docai/annotations/document_annotation_with_image.py
docai/annotations/image_utils.py
docai/annotations/layoutlm_utils.py
docai/annotations/ner_utils.py
docai/common/__init__.py
docai/common/base_client.py
docai/common/file_utils.py
docai/common/http_utils.py
docai/common/types.py
docai/generated/__init__.py
docai/generated/api/__init__.py
docai/generated/api/apps/__init__.py
docai/generated/api/apps/get_app_run_status.py
docai/generated/api/apps/get_document_extraction_results.py
docai/generated/api/apps/upload_documents.py
docai/generated/api/auth/__init__.py
docai/generated/api/auth/login.py
docai/generated/api/billing/__init__.py
docai/generated/api/billing/create_portal_link.py
docai/generated/api/billing/create_subscription_link.py
docai/generated/api/billing/get_billing_config.py
docai/generated/api/billing/get_subscription_v2.py
docai/generated/api/billing/run_webhook.py
docai/generated/api/create_doc_type_jobs/__init__.py
docai/generated/api/create_doc_type_jobs/create_doc_type.py
docai/generated/api/default/__init__.py
docai/generated/api/default/get_environment.py
docai/generated/api/default/get_metrics.py
docai/generated/api/default/health_check.py
docai/generated/api/document_types/__init__.py
docai/generated/api/document_types/delete_document_type.py
docai/generated/api/document_types/delete_test_document.py
docai/generated/api/document_types/delete_training_document.py
docai/generated/api/document_types/get_all_document_types.py
docai/generated/api/document_types/get_document_type.py
docai/generated/api/document_types/get_document_type_info.py
docai/generated/api/document_types/get_document_type_schema.py
docai/generated/api/document_types/get_document_type_settings.py
docai/generated/api/document_types/get_paginated_test_documents.py
docai_py-0.1.1.dist-info/LICENSE
docai_py-0.1.1.dist-info/WHEEL
docai_py-0.1.1.dist-info/METADATA
docai_py-0.1.1.dist-info/RECORD
