Metadata-Version: 2.1
Name: docai-py
Version: 0.1.1
Summary: Butler Doc AI
Home-page: https://butlerlabs.ai
License: Apache-2.0
Keywords: Document AI,Document Processing,OCR,LayoutLM
Author: Butler Labs
Author-email: support@butlerlabs.ai
Requires-Python: >=3.7,<4.0
Classifier: License :: OSI Approved :: Apache Software License
Classifier: Programming Language :: Python :: 3
Classifier: Programming Language :: Python :: 3.7
Classifier: Programming Language :: Python :: 3.8
Classifier: Programming Language :: Python :: 3.9
Classifier: Programming Language :: Python :: 3.10
Classifier: Programming Language :: Python :: 3.11
Requires-Dist: attrs (>=21.3.0,<23.0.0)
Requires-Dist: evaluate (>=0.3.0,<0.4.0)
Requires-Dist: httpx (>=0.15.4,<0.24.0)
Requires-Dist: numpy (>=1.17.0,<2.0.0)
Requires-Dist: pdf2image (>=1.14.0,<2.0.0)
Requires-Dist: pillow (>=8.0.0,<10.0.0)
Requires-Dist: python-dateutil (>=2.8.1,<2.9.0)
Requires-Dist: seqeval (>=1.2.2,<2.0.0)
Requires-Dist: transformers (>=4.20.0,<5.0.0)
Requires-Dist: typing-extensions (>=4.0.0,<5.0.0)
Project-URL: Documentation, https://docs.butlerlabs.ai
